{"cameraMode":{"drawMode":0,"name":"Shaded","section":"Shading Mode"},"sceneLighting":true,"audioPlay":false,"sceneViewState":{"m_AlwaysRefresh":false,"showFog":true,"showSkybox":true,"showFlares":true,"showImageEffects":true,"showParticleSystems":true,"showVisualEffectGraphs":true,"m_FxEnabled":true},"in2DMode":false,"pivot":{"x":648.4000244140625,"y":855.0,"z":0.0},"rotation":{"x":0.29635530710220339,"y":-0.08521314710378647,"z":0.026570135727524759,"w":0.9510218501091003},"size":88.52762603759766,"orthographic":false}